{
	"name": "DF_RZToCZ_MXM_Production_EnergyMetricsEBIC",
	"properties": {
		"type": "MappingDataFlow",
		"typeProperties": {
			"sources": [
				{
					"dataset": {
						"referenceName": "DS_RawZone_Production_Mxm_EBICDaily",
						"type": "DatasetReference"
					},
					"name": "RawSrcEBIC"
				}
			],
			"sinks": [
				{
					"dataset": {
						"referenceName": "DS_Snk_Synapse_Prod_EnergyMetricsEBIC",
						"type": "DatasetReference"
					},
					"name": "SnkEnergyMetricsEBIC"
				}
			],
			"transformations": [
				{
					"name": "Select1"
				}
			],
			"scriptLines": [
				"source(output(",
				"          A1_TRANSFER_A2 as string,",
				"          A1_TRANSFER_U1 as string,",
				"          A1_TRANSFER_U2 as string,",
				"          A2_ACTUAL_MONTHLY_BUDGET as string,",
				"          A2_ASSETUTILRATE as string,",
				"          A2_BUDGET_MONTHLY as string,",
				"          A2_CAPACITYEFFRATE as string,",
				"          A2_CONTINUOUS_OPERATING_DAYS as string,",
				"          A2_DOWNTIME as string,",
				"          A2_ENERGYEFFICIENCY as string,",
				"          A2_ONSTREAM_DAYS as string,",
				"          A2_ONSTREAM_FACTOR as string,",
				"          A2_PRODUCTION as string,",
				"          A2_PROD_MTD as string,",
				"          A2_TRANSFER_A1 as string,",
				"          A2_TRANSFER_U1 as string,",
				"          A2_TRANSFER_U2 as string,",
				"          ACTUAL_MONTHLY_BUDGET as string,",
				"          AMMONIASITETANK_TRANSFER_UREA1 as string,",
				"          AMMONIASITETANK_TRANSFER_UREA2 as string,",
				"          AMMONIA_DISPATCH_SHIP1 as string,",
				"          AMMONIA_DISPATCH_SHIP2 as string,",
				"          AMMONIA_TRANSFER_VALUE1 as string,",
				"          AMMONIA_TRANSFER_VALUE2 as string,",
				"          ASSETUTILRATE as string,",
				"          BOILER1 as string,",
				"          BOILER1_GJ as string,",
				"          BOILER2 as string,",
				"          BOILER2_GJ as string,",
				"          BOILER3 as string,",
				"          BOILER3_GJ as string,",
				"          BOILER4 as string,",
				"          BOILER4_GJ as string,",
				"          BOILER5 as string,",
				"          BOILER5_GJ as string,",
				"          BUDGET_MONTHLY as string,",
				"          CAPACITYEFFRATE as string,",
				"          CO2_CONS_UREA1 as string,",
				"          CO2_CONS_UREA2 as string,",
				"          CO2_EM_A1 as string,",
				"          CO2_EM_A2 as string,",
				"          CO2_EM_F1_BOILER as string,",
				"          CO2_EM_F2_BOILER as string,",
				"          CO2_EM_GLOBAL as string,",
				"          CO2_EM_SP_A1 as string,",
				"          CO2_EM_SP_A2 as string,",
				"          CO2_EM_SP_F1_STEAM as string,",
				"          CO2_EM_SP_F2_STEAM as string,",
				"          CONS_A1FG as string,",
				"          CONS_A1FG_GJ as string,",
				"          CONS_A1FG_HERMVL as string,",
				"          CONS_A1FG_HERMVL_GJ as string,",
				"          CONS_A1PG as string,",
				"          CONS_A1PG_GJ as string,",
				"          CONS_A2FG as string,",
				"          CONS_A2FG_GJ as string,",
				"          CONS_A2FG_HERMVL as string,",
				"          CONS_A2FG_HERMVL_GJ as string,",
				"          CONS_A2PG as string,",
				"          CONS_A2PG_GJ as string,",
				"          CONTINUOUS_OPERATING_DAYS as string,",
				"          DAILY_AMMONIA_2_SALE_VOL as string,",
				"          DAILY_AMMONIA_SALE_VOL as string,",
				"          DAILY_UREA_2_SALE_VOL as string,",
				"          DAILY_UREA_SALE_PORTSTORAGE1 as string,",
				"          DAILY_UREA_SALE_PORTSTORAGE2 as string,",
				"          DAILY_UREA_SALE_PS1_BAGS as string,",
				"          DAILY_UREA_SALE_PS1_BAGS_T as string,",
				"          DAILY_UREA_SALE_PS2_BAGS as string,",
				"          DAILY_UREA_SALE_PS2_BAGS_T as string,",
				"          DAILY_UREA_SALE_VOL as string,",
				"          DAILY_UREA_SALE_VOL_BAGS as string,",
				"          DAILY_UREA_SALE_VOL_BAGS_T as string,",
				"          DOWNTIME as string,",
				"          ELEC_AV_PG1 as string,",
				"          ELEC_AV_PG2 as string,",
				"          ELEC_FL_AMMONIA1 as string,",
				"          ELEC_FL_AMMONIA2 as string,",
				"          ELEC_FL_SP_CONS_1 as string,",
				"          ELEC_FL_SP_CONS_2 as string,",
				"          ELEC_FL_TOT_IMPORT_1 as string,",
				"          ELEC_FL_TOT_IMPORT_2 as string,",
				"          ELEC_FL_TOT_POWGEN_1 as string,",
				"          ELEC_FL_UREA1 as string,",
				"          ELEC_FL_UREA2 as string,",
				"          ELEC_GRID_TOTAL as string,",
				"          ELEC_OUTSIDE_GRID1 as string,",
				"          ELEC_OUTSIDE_GRID2 as string,",
				"          ELEC_PG1 as string,",
				"          ELEC_PG2 as string,",
				"          ELEC_SP_CONS1_STEAM as string,",
				"          ELEC_SP_CONS2_STEAM as string,",
				"          ELEC_TOTAL_CONSUMPTION as string,",
				"          ENERGYEFFICIENCY as string,",
				"          FGH_PRODUCTIONID as string,",
				"          NM3_BOILER1 as string,",
				"          NM3_BOILER2 as string,",
				"          NM3_BOILER3 as string,",
				"          NM3_BOILER4 as string,",
				"          NM3_BOILER5 as string,",
				"          ONSTREAMFACTOR as string,",
				"          ONSTREAM_DAYS as string,",
				"          PLANT as string,",
				"          PRODUCTION as string,",
				"          PRODUCTIONDATE as string,",
				"          PROD_MTD as string,",
				"          REMARKS as string,",
				"          REMARKS_LONGDESCRIPTION as string,",
				"          SECOND_GRADE_UREA_PS1 as string,",
				"          SECOND_GRADE_UREA_PS2 as string,",
				"          SHIP_1 as string,",
				"          SHIP_2 as string,",
				"          SITE as string,",
				"          SP_CO2_TON_UREA1 as string,",
				"          SP_CO2_TON_UREA2 as string,",
				"          SP_CONS_A1FG as string,",
				"          SP_CONS_A1FG_HERMVL as string,",
				"          SP_CONS_A1PG as string,",
				"          SP_CONS_A2FG as string,",
				"          SP_CONS_A2FG_HERMVL as string,",
				"          SP_CONS_A2PG as string,",
				"          STATUS as string,",
				"          STATUSDATE as string,",
				"          STEAM_BOILER1 as string,",
				"          STEAM_BOILER2 as string,",
				"          STEAM_BOILER3 as string,",
				"          STEAM_BOILER4 as string,",
				"          STEAM_BOILER5 as string,",
				"          STEAM_TOTAL as string,",
				"          STEAM_TOTAL1 as string,",
				"          STEAM_TOTAL2 as string,",
				"          STEAM_TO_GENERATOR1 as string,",
				"          STEAM_TO_GENERATOR2 as string,",
				"          TOTAL_CONS_FG as string,",
				"          TOTAL_CONS_FG_GJ as string,",
				"          TOTAL_CONS_NG as string,",
				"          TOTAL_CONS_NG_GJ as string,",
				"          TOTAL_CONS_NM3_FG as string,",
				"          TOTAL_CONS_NM3_NG as string,",
				"          TOTAL_CONS_NM3_PG as string,",
				"          TOTAL_CONS_PG as string,",
				"          TOTAL_CONS_PG_GJ as string,",
				"          TOTAL_GAS_CONS_1 as string,",
				"          TOTAL_GAS_CONS_1_GJ as string,",
				"          TOTAL_GAS_CONS_2 as string,",
				"          TOTAL_GAS_CONS_2_GJ as string,",
				"          TOTAL_SEA_WATER as string,",
				"          TOTAL_SP_GAS_CONS_1 as string,",
				"          TOTAL_SP_GAS_CONS_2 as string,",
				"          TRANSDATE as string,",
				"          TRANSFER_TO_PORTSTORAGE1 as string,",
				"          TRANSFER_TO_PORTSTORAGE2 as string,",
				"          U1_ACTUAL_MONTHLY_BUDGET as string,",
				"          U1_ASSETUTILRATE as string,",
				"          U1_BUDGET_MONTHLY as string,",
				"          U1_CAPACITYEFFRATE as string,",
				"          U1_CONTINUOUS_OPERATING_DAYS as string,",
				"          U1_DOWNTIME as string,",
				"          U1_ENERGYEFFICIENCY as string,",
				"          U1_ONSTREAMFACTOR as string,",
				"          U1_ONSTREAM_DAYS as string,",
				"          U1_PRODUCTION as string,",
				"          U1_PROD_MTD as string,",
				"          U2_ACTUAL_MONTHLY_BUDGET as string,",
				"          U2_ASSETUTILRATE as string,",
				"          U2_BUDGET_MONTHLY as string,",
				"          U2_CAPACITYEFFRATE as string,",
				"          U2_CONTINUOUS_OPERATING_DAYS as string,",
				"          U2_DOWNTIME as string,",
				"          U2_ENERGYEFFICIENCY as string,",
				"          U2_ONSTREAM_DAYS as string,",
				"          U2_ONSTREAM_FACTOR as string,",
				"          U2_PRODUCTION as string,",
				"          U2_PROD_MTD as string,",
				"          UREA1_DISPATCH_SHIP1 as string,",
				"          UREA1_DISPATCH_SHIP2 as string,",
				"          UREA1_DISPATCH_TRUCK as string,",
				"          UREA2_DISPATCH_SHIP1 as string,",
				"          UREA2_DISPATCH_SHIP2 as string,",
				"          UREA2_DISPATCH_TRUCK as string,",
				"          WATER_DESLT_IMPORT_1 as string,",
				"          WATER_DESLT_IMPORT_2 as string,",
				"          WATER_DESLT_SP_UREA1 as string,",
				"          WATER_DESLT_SP_UREA2 as string,",
				"          WATER_INSIDE as string,",
				"          WATER_INSIDE2 as string,",
				"          WATER_INSIDE_RO2 as string,",
				"          WATER_OUTSIDE as string,",
				"          WATER_OUTSIDE2 as string,",
				"          WATER_OUTSIDE2_EBIC as string,",
				"          WATER_OUTSIDE2_SDIC as string,",
				"          WATER_OUTSIDE_EBIC as string,",
				"          WATER_TOTAL as string,",
				"          WATER_TOTAL2 as string",
				"     ),",
				"     allowSchemaDrift: true,",
				"     validateSchema: false,",
				"     ignoreNoFilesFound: true) ~> RawSrcEBIC",
				"RawSrcEBIC select(mapColumn(",
				"          PRODUCTIONDATE,",
				"          PLANT,",
				"          STATUS,",
				"          STATUSDATE,",
				"          REMARKS,",
				"          CONS_A1PG,",
				"          CONS_A1FG,",
				"          BOILER1,",
				"          TOTAL_CONS_NG,",
				"          CONS_A1PG_GJ,",
				"          CONS_A1FG_GJ,",
				"          BOILER1_GJ,",
				"          TOTAL_CONS_NG_GJ,",
				"          SP_CONS_A1PG,",
				"          SP_CONS_A1FG,",
				"          NM3_BOILER1,",
				"          TOTAL_CONS_NM3_NG,",
				"          CO2_EM_A1,",
				"          CO2_EM_SP_A1,",
				"          CO2_EM_F1_BOILER,",
				"          CO2_EM_SP_F1_STEAM,",
				"          CO2_EM_GLOBAL,",
				"          STEAM_BOILER1,",
				"          STEAM_TOTAL,",
				"          ELEC_PG1,",
				"          ELEC_OUTSIDE_GRID1,",
				"          ELEC_AV_PG1,",
				"          ELEC_SP_CONS1_STEAM,",
				"          ELEC_TOTAL_CONSUMPTION,",
				"          STEAM_TO_GENERATOR1,",
				"          WATER_OUTSIDE,",
				"          WATER_INSIDE,",
				"          WATER_TOTAL",
				"     ),",
				"     skipDuplicateMapInputs: true,",
				"     skipDuplicateMapOutputs: true) ~> Select1",
				"Select1 sink(allowSchemaDrift: true,",
				"     validateSchema: false,",
				"     input(",
				"          PRODUCTIONDATE as date,",
				"          PLANT as string,",
				"          STATUS as string,",
				"          STATUSDATE as date,",
				"          REMARKS as string,",
				"          CONS_A1PG as decimal(25,8),",
				"          CONS_A1FG as decimal(25,8),",
				"          BOILER1 as decimal(25,8),",
				"          TOTAL_CONS_NG as decimal(25,8),",
				"          CONS_A1PG_GJ as decimal(25,8),",
				"          CONS_A1FG_GJ as decimal(25,8),",
				"          BOILER1_GJ as decimal(25,8),",
				"          TOTAL_CONS_NG_GJ as decimal(25,8),",
				"          SP_CONS_A1PG as decimal(25,8),",
				"          SP_CONS_A1FG as decimal(25,8),",
				"          NM3_BOILER1 as decimal(25,8),",
				"          TOTAL_CONS_NM3_NG as decimal(25,8),",
				"          CO2_EM_A1 as decimal(25,8),",
				"          CO2_EM_SP_A1 as decimal(25,8),",
				"          CO2_EM_F1_BOILER as decimal(25,8),",
				"          CO2_EM_SP_F1_STEAM as decimal(25,8),",
				"          CO2_EM_GLOBAL as decimal(25,8),",
				"          STEAM_BOILER1 as decimal(25,8),",
				"          STEAM_TOTAL as decimal(25,8),",
				"          ELEC_PG1 as decimal(25,8),",
				"          ELEC_OUTSIDE_GRID1 as decimal(25,8),",
				"          ELEC_AV_PG1 as decimal(25,8),",
				"          ELEC_SP_CONS1_STEAM as decimal(25,8),",
				"          ELEC_TOTAL_CONSUMPTION as decimal(25,8),",
				"          STEAM_TO_GENERATOR1 as decimal(25,8),",
				"          WATER_OUTSIDE as decimal(25,8),",
				"          WATER_INSIDE as decimal(25,8),",
				"          WATER_TOTAL as decimal(25,8)",
				"     ),",
				"     deletable:false,",
				"     insertable:true,",
				"     updateable:false,",
				"     upsertable:false,",
				"     format: 'table',",
				"     staged: true,",
				"     allowCopyCommand: true,",
				"     skipDuplicateMapInputs: true,",
				"     skipDuplicateMapOutputs: true,",
				"     errorHandlingOption: 'stopOnFirstError',",
				"     mapColumn(",
				"          PRODUCTIONDATE,",
				"          PLANT,",
				"          STATUS,",
				"          STATUSDATE,",
				"          REMARKS,",
				"          CONS_A1PG,",
				"          CONS_A1FG,",
				"          BOILER1,",
				"          TOTAL_CONS_NG,",
				"          CONS_A1PG_GJ,",
				"          CONS_A1FG_GJ,",
				"          BOILER1_GJ,",
				"          TOTAL_CONS_NG_GJ,",
				"          SP_CONS_A1PG,",
				"          SP_CONS_A1FG,",
				"          NM3_BOILER1,",
				"          TOTAL_CONS_NM3_NG,",
				"          CO2_EM_A1,",
				"          CO2_EM_SP_A1,",
				"          CO2_EM_F1_BOILER,",
				"          CO2_EM_SP_F1_STEAM,",
				"          CO2_EM_GLOBAL,",
				"          STEAM_BOILER1,",
				"          STEAM_TOTAL,",
				"          ELEC_PG1,",
				"          ELEC_OUTSIDE_GRID1,",
				"          ELEC_AV_PG1,",
				"          ELEC_SP_CONS1_STEAM,",
				"          ELEC_TOTAL_CONSUMPTION,",
				"          STEAM_TO_GENERATOR1,",
				"          WATER_OUTSIDE,",
				"          WATER_INSIDE,",
				"          WATER_TOTAL",
				"     )) ~> SnkEnergyMetricsEBIC"
			]
		}
	}
}