{
	"name": "PL_Manual_Finance_WeeklyFreeCashFlow",
	"properties": {
		"activities": [
			{
				"name": "spc_LoadWeeklyFreeCashFlow",
				"type": "SqlPoolStoredProcedure",
				"dependsOn": [
					{
						"activity": "RZToCZ_Manual_Finance_WeeklyFreeCashFlo",
						"dependencyConditions": [
							"Succeeded"
						]
					}
				],
				"policy": {
					"timeout": "0.12:00:00",
					"retry": 0,
					"retryIntervalInSeconds": 30,
					"secureOutput": false,
					"secureInput": false
				},
				"userProperties": [],
				"sqlPool": {
					"referenceName": "synwsdb01",
					"type": "SqlPoolReference"
				},
				"typeProperties": {
					"storedProcedureName": "[consumption].[spc_LoadWeeklyFreeCashFlow]"
				}
			},
			{
				"name": "CD_Archive_Finance_Manual_WeeklyFreeCashFlow",
				"type": "Copy",
				"dependsOn": [
					{
						"activity": "spc_LoadWeeklyFreeCashFlow",
						"dependencyConditions": [
							"Succeeded"
						]
					}
				],
				"policy": {
					"timeout": "0.12:00:00",
					"retry": 0,
					"retryIntervalInSeconds": 30,
					"secureOutput": false,
					"secureInput": false
				},
				"userProperties": [],
				"typeProperties": {
					"source": {
						"type": "ExcelSource",
						"storeSettings": {
							"type": "AzureBlobFSReadSettings",
							"recursive": true,
							"enablePartitionDiscovery": false
						}
					},
					"sink": {
						"type": "DelimitedTextSink",
						"storeSettings": {
							"type": "AzureBlobFSWriteSettings"
						},
						"formatSettings": {
							"type": "DelimitedTextWriteSettings",
							"quoteAllText": true,
							"fileExtension": ".txt"
						}
					},
					"enableStaging": false,
					"translator": {
						"type": "TabularTranslator",
						"typeConversion": true,
						"typeConversionSettings": {
							"allowDataTruncation": true,
							"treatBooleanAsNumber": false
						}
					}
				},
				"inputs": [
					{
						"referenceName": "DS_LandingZone_Finance_Manual_WeeklyFreeCashFlow",
						"type": "DatasetReference"
					}
				],
				"outputs": [
					{
						"referenceName": "DS_LandingZone_Finance_Manual_Archive_WeeklyFreeCashFlow",
						"type": "DatasetReference"
					}
				]
			},
			{
				"name": "spc_ExecutionLogEntry_Start",
				"type": "SqlPoolStoredProcedure",
				"dependsOn": [],
				"policy": {
					"timeout": "0.12:00:00",
					"retry": 0,
					"retryIntervalInSeconds": 30,
					"secureOutput": false,
					"secureInput": false
				},
				"userProperties": [],
				"sqlPool": {
					"referenceName": "synwsdb01",
					"type": "SqlPoolReference"
				},
				"typeProperties": {
					"storedProcedureName": "[consumption].[spc_ExecutionLogEntry]",
					"storedProcedureParameters": {
						"DataLoadStage": {
							"value": "ManualExtractsLoad",
							"type": "String"
						},
						"DataLoadStatus": {
							"value": "Started",
							"type": "String"
						},
						"DataRefreshDate": {
							"value": null,
							"type": "DateTime"
						},
						"EndTime": {
							"value": null,
							"type": "DateTime"
						},
						"ErrorID": {
							"value": null,
							"type": "String"
						},
						"ErrorMessage": {
							"value": null,
							"type": "String"
						},
						"ExecutionID": {
							"value": {
								"value": "@pipeline().RunId",
								"type": "Expression"
							},
							"type": "String"
						},
						"PipelineName": {
							"value": {
								"value": "@pipeline().Pipeline",
								"type": "Expression"
							},
							"type": "String"
						},
						"StartTime": {
							"value": {
								"value": "@pipeline().TriggerTime",
								"type": "Expression"
							},
							"type": "DateTime"
						},
						"DataCategory": {
							"value": "Finance",
							"type": "String"
						}
					}
				}
			},
			{
				"name": "spc_ExecutionLogEntry_End",
				"type": "SqlPoolStoredProcedure",
				"dependsOn": [
					{
						"activity": "CD_Archive_Finance_Manual_WeeklyFreeCashFlow",
						"dependencyConditions": [
							"Succeeded"
						]
					}
				],
				"policy": {
					"timeout": "0.12:00:00",
					"retry": 0,
					"retryIntervalInSeconds": 30,
					"secureOutput": false,
					"secureInput": false
				},
				"userProperties": [],
				"sqlPool": {
					"referenceName": "synwsdb01",
					"type": "SqlPoolReference"
				},
				"typeProperties": {
					"storedProcedureName": "[consumption].[spc_ExecutionLogEntry]",
					"storedProcedureParameters": {
						"DataLoadStage": {
							"value": "ManualExtractsLoad",
							"type": "String"
						},
						"DataLoadStatus": {
							"value": "Completed",
							"type": "String"
						},
						"DataRefreshDate": {
							"value": null,
							"type": "DateTime"
						},
						"EndTime": {
							"value": {
								"value": "@convertToUtc(utcNow(),'UTC')",
								"type": "Expression"
							},
							"type": "DateTime"
						},
						"ErrorID": {
							"value": null,
							"type": "String"
						},
						"ErrorMessage": {
							"value": null,
							"type": "String"
						},
						"ExecutionID": {
							"value": {
								"value": "@pipeline().RunId",
								"type": "Expression"
							},
							"type": "String"
						},
						"PipelineName": {
							"value": {
								"value": "@pipeline().Pipeline",
								"type": "Expression"
							},
							"type": "String"
						},
						"StartTime": {
							"value": null,
							"type": "DateTime"
						},
						"DataCategory": {
							"value": "Finance",
							"type": "String"
						}
					}
				}
			},
			{
				"name": "spc_ExecutionLogEntry_Error_SrcToRZ",
				"type": "SqlPoolStoredProcedure",
				"dependsOn": [
					{
						"activity": "SrcToRZ_Manual_Finance_WeeklyFreeCashFlow",
						"dependencyConditions": [
							"Failed"
						]
					}
				],
				"policy": {
					"timeout": "0.12:00:00",
					"retry": 0,
					"retryIntervalInSeconds": 30,
					"secureOutput": false,
					"secureInput": false
				},
				"userProperties": [],
				"sqlPool": {
					"referenceName": "synwsdb01",
					"type": "SqlPoolReference"
				},
				"typeProperties": {
					"storedProcedureName": "[consumption].[spc_ExecutionLogEntry]",
					"storedProcedureParameters": {
						"DataLoadStage": {
							"value": "ManualExtractsLoad",
							"type": "String"
						},
						"DataLoadStatus": {
							"value": "Error",
							"type": "String"
						},
						"DataRefreshDate": {
							"value": null,
							"type": "DateTime"
						},
						"EndTime": {
							"value": {
								"value": "@pipeline().TriggerTime",
								"type": "Expression"
							},
							"type": "DateTime"
						},
						"ErrorID": {
							"value": {
								"value": "@activity('SrcToRZ_Manual_Finance_WeeklyFreeCashFlow').Error.errorCode",
								"type": "Expression"
							},
							"type": "String"
						},
						"ErrorMessage": {
							"value": {
								"value": "@activity('SrcToRZ_Manual_Finance_WeeklyFreeCashFlow').Error.message",
								"type": "Expression"
							},
							"type": "String"
						},
						"ExecutionID": {
							"value": {
								"value": "@pipeline().RunId",
								"type": "Expression"
							},
							"type": "String"
						},
						"PipelineName": {
							"value": {
								"value": "@pipeline().Pipeline",
								"type": "Expression"
							},
							"type": "String"
						},
						"StartTime": {
							"value": null,
							"type": "DateTime"
						},
						"DataCategory": {
							"value": "Finance",
							"type": "String"
						}
					}
				}
			},
			{
				"name": "spc_ExecutionLogEntry_Error_SrcToRZ_copy1",
				"type": "SqlPoolStoredProcedure",
				"dependsOn": [
					{
						"activity": "RZToCZ_Manual_Finance_WeeklyFreeCashFlo",
						"dependencyConditions": [
							"Failed"
						]
					}
				],
				"policy": {
					"timeout": "0.12:00:00",
					"retry": 0,
					"retryIntervalInSeconds": 30,
					"secureOutput": false,
					"secureInput": false
				},
				"userProperties": [],
				"sqlPool": {
					"referenceName": "synwsdb01",
					"type": "SqlPoolReference"
				},
				"typeProperties": {
					"storedProcedureName": "[consumption].[spc_ExecutionLogEntry]",
					"storedProcedureParameters": {
						"DataLoadStage": {
							"value": "ManualExtractsLoad",
							"type": "String"
						},
						"DataLoadStatus": {
							"value": "Error",
							"type": "String"
						},
						"DataRefreshDate": {
							"value": null,
							"type": "DateTime"
						},
						"EndTime": {
							"value": {
								"value": "@pipeline().TriggerTime",
								"type": "Expression"
							},
							"type": "DateTime"
						},
						"ErrorID": {
							"value": {
								"value": "@activity('RZToCZ_Manual_Finance_WeeklyFreeCashFlo').Error.errorCode",
								"type": "Expression"
							},
							"type": "String"
						},
						"ErrorMessage": {
							"value": {
								"value": "@activity('RZToCZ_Manual_Finance_WeeklyFreeCashFlo').Error.message",
								"type": "Expression"
							},
							"type": "String"
						},
						"ExecutionID": {
							"value": {
								"value": "@pipeline().RunId",
								"type": "Expression"
							},
							"type": "String"
						},
						"PipelineName": {
							"value": {
								"value": "@pipeline().Pipeline",
								"type": "Expression"
							},
							"type": "String"
						},
						"StartTime": {
							"value": null,
							"type": "DateTime"
						},
						"DataCategory": {
							"value": "Finance",
							"type": "String"
						}
					}
				}
			},
			{
				"name": "spc_ExecutionLogEntry_Error_SrcToRZ_copy1_copy1",
				"type": "SqlPoolStoredProcedure",
				"dependsOn": [
					{
						"activity": "spc_LoadWeeklyFreeCashFlow",
						"dependencyConditions": [
							"Failed"
						]
					}
				],
				"policy": {
					"timeout": "0.12:00:00",
					"retry": 0,
					"retryIntervalInSeconds": 30,
					"secureOutput": false,
					"secureInput": false
				},
				"userProperties": [],
				"sqlPool": {
					"referenceName": "synwsdb01",
					"type": "SqlPoolReference"
				},
				"typeProperties": {
					"storedProcedureName": "[consumption].[spc_ExecutionLogEntry]",
					"storedProcedureParameters": {
						"DataLoadStage": {
							"value": "ManualExtractsLoad",
							"type": "String"
						},
						"DataLoadStatus": {
							"value": "Error",
							"type": "String"
						},
						"DataRefreshDate": {
							"value": null,
							"type": "DateTime"
						},
						"EndTime": {
							"value": {
								"value": "@pipeline().TriggerTime",
								"type": "Expression"
							},
							"type": "DateTime"
						},
						"ErrorID": {
							"value": {
								"value": "@activity('spc_LoadWeeklyFreeCashFlow').Error.errorCode",
								"type": "Expression"
							},
							"type": "String"
						},
						"ErrorMessage": {
							"value": {
								"value": "@activity('spc_LoadWeeklyFreeCashFlow').Error.message",
								"type": "Expression"
							},
							"type": "String"
						},
						"ExecutionID": {
							"value": {
								"value": "@pipeline().RunId",
								"type": "Expression"
							},
							"type": "String"
						},
						"PipelineName": {
							"value": {
								"value": "@pipeline().Pipeline",
								"type": "Expression"
							},
							"type": "String"
						},
						"StartTime": {
							"value": null,
							"type": "DateTime"
						},
						"DataCategory": {
							"value": "Finance",
							"type": "String"
						}
					}
				}
			},
			{
				"name": "spc_ExecutionLogEntry_Error_SrcToRZ_copy1_copy1_copy1",
				"type": "SqlPoolStoredProcedure",
				"dependsOn": [
					{
						"activity": "CD_Archive_Finance_Manual_WeeklyFreeCashFlow",
						"dependencyConditions": [
							"Failed"
						]
					}
				],
				"policy": {
					"timeout": "0.12:00:00",
					"retry": 0,
					"retryIntervalInSeconds": 30,
					"secureOutput": false,
					"secureInput": false
				},
				"userProperties": [],
				"sqlPool": {
					"referenceName": "synwsdb01",
					"type": "SqlPoolReference"
				},
				"typeProperties": {
					"storedProcedureName": "[consumption].[spc_ExecutionLogEntry]",
					"storedProcedureParameters": {
						"DataLoadStage": {
							"value": "ManualExtractsLoad",
							"type": "String"
						},
						"DataLoadStatus": {
							"value": "Error",
							"type": "String"
						},
						"DataRefreshDate": {
							"value": null,
							"type": "DateTime"
						},
						"EndTime": {
							"value": {
								"value": "@pipeline().TriggerTime",
								"type": "Expression"
							},
							"type": "DateTime"
						},
						"ErrorID": {
							"value": {
								"value": "@activity('CD_Archive_Finance_Manual_WeeklyFreeCashFlow').Error.errorCode",
								"type": "Expression"
							},
							"type": "String"
						},
						"ErrorMessage": {
							"value": {
								"value": "@activity('CD_Archive_Finance_Manual_WeeklyFreeCashFlow').Error.message",
								"type": "Expression"
							},
							"type": "String"
						},
						"ExecutionID": {
							"value": {
								"value": "@pipeline().RunId",
								"type": "Expression"
							},
							"type": "String"
						},
						"PipelineName": {
							"value": {
								"value": "@pipeline().Pipeline",
								"type": "Expression"
							},
							"type": "String"
						},
						"StartTime": {
							"value": null,
							"type": "DateTime"
						},
						"DataCategory": {
							"value": "Finance",
							"type": "String"
						}
					}
				}
			},
			{
				"name": "SrcToRZ_Manual_Finance_WeeklyFreeCashFlow",
				"description": "Import data from DS_LandingZone_Finance_Manual_WeeklyFreeCashFlow",
				"type": "Copy",
				"dependsOn": [
					{
						"activity": "spc_ExecutionLogEntry_Start",
						"dependencyConditions": [
							"Succeeded"
						]
					}
				],
				"policy": {
					"timeout": "0.12:00:00",
					"retry": 0,
					"retryIntervalInSeconds": 30,
					"secureOutput": false,
					"secureInput": false
				},
				"userProperties": [],
				"typeProperties": {
					"source": {
						"type": "ExcelSource",
						"storeSettings": {
							"type": "AzureBlobFSReadSettings",
							"recursive": true,
							"enablePartitionDiscovery": false
						}
					},
					"sink": {
						"type": "DelimitedTextSink",
						"storeSettings": {
							"type": "AzureBlobFSWriteSettings"
						},
						"formatSettings": {
							"type": "DelimitedTextWriteSettings",
							"quoteAllText": true,
							"fileExtension": ".txt"
						}
					},
					"enableStaging": false,
					"translator": {
						"type": "TabularTranslator",
						"typeConversion": true,
						"typeConversionSettings": {
							"allowDataTruncation": true,
							"treatBooleanAsNumber": false
						}
					}
				},
				"inputs": [
					{
						"referenceName": "DS_LandingZone_Finance_Manual_WeeklyFreeCashFlow",
						"type": "DatasetReference"
					}
				],
				"outputs": [
					{
						"referenceName": "DS_ADLSRawZone",
						"type": "DatasetReference",
						"parameters": {
							"FolderName": "ManualExtracts",
							"FileName": "WeeklyFreeCashFlow",
							"MainFolderName": "Finance"
						}
					}
				]
			},
			{
				"name": "RZToCZ_Manual_Finance_WeeklyFreeCashFlo",
				"type": "ExecuteDataFlow",
				"dependsOn": [
					{
						"activity": "SrcToRZ_Manual_Finance_WeeklyFreeCashFlow",
						"dependencyConditions": [
							"Succeeded"
						]
					}
				],
				"policy": {
					"timeout": "0.12:00:00",
					"retry": 0,
					"retryIntervalInSeconds": 30,
					"secureOutput": false,
					"secureInput": false
				},
				"userProperties": [],
				"typeProperties": {
					"dataflow": {
						"referenceName": "DF_RZToCZ_Manual_Finance_WeeklyFreeCashFlow",
						"type": "DataFlowReference"
					},
					"staging": {
						"linkedService": {
							"referenceName": "syn-ws-dlk-dev-01-WorkspaceDefaultStorage",
							"type": "LinkedServiceReference"
						},
						"folderPath": "ferti-dl-raw-dev/SynapseInternal"
					},
					"compute": {
						"coreCount": 8,
						"computeType": "General"
					},
					"traceLevel": "Fine"
				}
			}
		],
		"folder": {
			"name": "Finance/ManualExtracts"
		},
		"annotations": [],
		"lastPublishTime": "2023-05-23T06:06:32Z"
	},
	"type": "Microsoft.Synapse/workspaces/pipelines"
}